pyfj/__init__.py
pyfj/cli.py
pyfj-0.1.2.dist-info/METADATA
pyfj-0.1.2.dist-info/WHEEL
pyfj-0.1.2.dist-info/entry_points.txt
pyfj-0.1.2.dist-info/RECORD
