Metadata-Version: 2.3
Name: pyfj
Version: 0.1.2
Summary: A tool for creating django-ninja projects
Author: gaojian
Author-email: olivetree123@163.com
Requires-Python: >=3.10
Classifier: Programming Language :: Python :: 3
Classifier: Programming Language :: Python :: 3.10
Classifier: Programming Language :: Python :: 3.11
Classifier: Programming Language :: Python :: 3.12
Classifier: Programming Language :: Python :: 3.13
Requires-Dist: click (>=8.1.8,<9.0.0)
